phishing_detection_engine/__init__.py
phishing_detection_engine/functions.py
phishing_detection_engine/trained_model/__init__.py
phishing_detection_engine/trained_model/finalized_model.sav
tests/__init__.py
tests/test_functions.py
phishing_detection_engine-0.0.17.dist-info/LICENSE
phishing_detection_engine-0.0.17.dist-info/METADATA
phishing_detection_engine-0.0.17.dist-info/WHEEL
phishing_detection_engine-0.0.17.dist-info/top_level.txt
phishing_detection_engine-0.0.17.dist-info/RECORD
