Metadata-Version: 2.1
Name: phishing-detection-engine
Version: 0.0.17
Summary: Library for Detecting Phishing URLs
Home-page: UNKNOWN
Author: HamzaAnjum_hamzaanjum9696
Author-email: hamzaanjum1@gmail.com
License: MIT
Platform: UNKNOWN
Requires-Dist: IPy
Requires-Dist: bs4
Requires-Dist: favicon
Requires-Dist: numpy (==1.18.5)
Requires-Dist: python-whois (==0.7.3)
Requires-Dist: requests
Requires-Dist: scikit-learn (==0.23.2)
Requires-Dist: scipy (==1.5.4)
Requires-Dist: selenium
Requires-Dist: tld
